{
  "title": "Project ScanGov",
  "description": "Government digital experience monitor",
  "url": "https://scangov.org",
  "org": "ScanGov",
  "org-url": "https://scangov.com",
  "repo": "https://github.com/ScanGov/scangov",
  "data_repo": "https://github.com/ScanGov/data",
  "rss": "https://docs.scangov.org/feed.xml",
  "github-url": "https://github.com/ScanGov/scangov",
  "linkedin-url": "https://www.linkedin.com/company/scangov",
  "twitter-url": "",
  "twitter-username": "",
  "twitter": "",
  "date": "%B %-d, %Y",
  "timezone": "America/Los_Angeles",
  "data": [
    "Accessibility",
    "Content",
    "Domain",
    "Performance",
    "SEO",
    "Security",
    "Social"
  ],
  "nav": [
    {
      "url": "/#sort",
      "title": "Filter",
      "icon": "filter"
    },
    {
      "url": "/changelog",
      "title": "Changelog",
      "icon": "timeline"
    },
    {
      "url": "/map",
      "title": "Map",
      "icon": "map"
    },
    {
      "url": "https://scangov.com/",
      "title": "ScanGov",
      "icon": "house"
    },
    {
      "url": "https://docs.scangov.org/",
      "title": "Docs",
      "icon": "file-lines"
    },
    {
      "url": "https://docs.scangov.org/about",
      "title": "About",
      "icon": "circle-info"
    }
  ]
}
